webhooks_git_automata/__init__.py
webhooks_git_automata/automata.py
webhooks_git_automata/providers.py
webhooks_git_automata/settings.py
webhooks_git_automata/webhooks.py
webhooks_git_automata/worker.py
webhooks_git_automata-0.0.3.dist-info/METADATA
webhooks_git_automata-0.0.3.dist-info/RECORD
webhooks_git_automata-0.0.3.dist-info/WHEEL
webhooks_git_automata-0.0.3.dist-info/entry_points.txt
webhooks_git_automata-0.0.3.dist-info/top_level.txt
