Metadata-Version: 2.1
Name: webhooks-git-automata
Version: 0.0.3
Summary: Webhook receiver for Git deployments
Home-page: https://github.com/alexbarcelo/webhooks-git-automata
Author: Alex Barcelo
Author-email: alex@betarho.net
License: UNKNOWN
Platform: UNKNOWN
Classifier: Programming Language :: Python :: 3
Classifier: License :: OSI Approved :: MIT License
Classifier: Operating System :: OS Independent
Requires-Dist: Flask
Requires-Dist: PyYAML
